{
    "ADaCGH2": [],
    "affycoretools": [
        "ReportingTools",
        "biovizBase",
        "ggbio"
    ],
    "AgiMicroRna": [
        "ReportingTools",
        "affycoretools",
        "biovizBase",
        "ggbio"
    ],
    "AHMassBank": [
        "AnnotationHubData"
    ],
    "alabaster": [
        "alabaster.spatial",
        "alabaster.vcf"
    ],
    "alabaster.spatial": [],
    "alabaster.vcf": [],
    "AllelicImbalance": [
        "Gviz",
        "biovizBase"
    ],
    "AnnotationHubData": [],
    "annotatr": [],
    "APAlyzer": [],
    "appreci8R": [],
    "arrayMvout": [
        "lumi",
        "methylumi"
    ],
    "ASpli": [
        "Gviz",
        "biovizBase"
    ],
    "ATACCoGAPS": [
        "chromVAR",
        "motifmatchr"
    ],
    "ATACseqQC": [
        "ChIPpeakAnno",
        "motifStack"
    ],
    "ATACseqTFEA": [
        "motifmatchr"
    ],
    "atSNP": [
        "motifStack"
    ],
    "autonomics": [],
    "BadRegionFinder": [],
    "bandle": [],
    "BBCAnalyzer": [],
    "beer": [
        "PhIPData"
    ],
    "benchdamic": [],
    "BGmix": [],
    "bigmelon": [
        "lumi",
        "methylumi",
        "wateRmelon"
    ],
    "BindingSiteFinder": [
        "Gviz",
        "biovizBase"
    ],
    "BioNAR": [],
    "biovizBase": [],
    "biscuiteer": [
        "annotatr",
        "dmrseq"
    ],
    "BOBaFIT": [
        "biovizBase",
        "ggbio"
    ],
    "borealis": [
        "DSS"
    ],
    "brainflowprobes": [
        "GenomicFiles",
        "biovizBase",
        "derfinder",
        "derfinderPlot",
        "ggbio"
    ],
    "BubbleTree": [
        "biovizBase"
    ],
    "BUSpaRse": [],
    "CAFE": [
        "biovizBase",
        "ggbio"
    ],
    "CAGEfightR": [
        "GenomicFiles",
        "GenomicInteractions",
        "Gviz",
        "biovizBase"
    ],
    "cageminer": [
        "biovizBase",
        "ggbio"
    ],
    "CAGEr": [
        "CAGEfightR",
        "GenomicFiles",
        "GenomicInteractions",
        "Gviz",
        "biovizBase"
    ],
    "canceR": [],
    "cardelino": [],
    "casper": [],
    "categoryCompare": [
        "RCy3"
    ],
    "cbaf": [
        "RTCGAToolbox",
        "cBioPortalData"
    ],
    "cBioPortalData": [
        "RTCGAToolbox"
    ],
    "CBNplot": [],
    "celda": [],
    "CeTF": [
        "RCy3"
    ],
    "CexoR": [],
    "cfDNAPro": [],
    "ChAMP": [
        "DMRcate",
        "DSS",
        "Gviz",
        "biovizBase",
        "lumi",
        "methylumi",
        "missMethyl",
        "wateRmelon"
    ],
    "ChIC": [],
    "chimeraviz": [
        "Gviz",
        "biovizBase"
    ],
    "ChIPexoQual": [
        "biovizBase"
    ],
    "ChIPpeakAnno": [],
    "ChIPQC": [
        "DiffBind"
    ],
    "ChIPXpress": [],
    "ChromSCape": [],
    "chromVAR": [],
    "cicero": [
        "Gviz",
        "biovizBase"
    ],
    "circRNAprofiler": [
        "gwascat"
    ],
    "CircSeqAlignTk": [],
    "cliProfiler": [],
    "CNVfilteR": [
        "CopyNumberPlots",
        "biovizBase",
        "karyoploteR"
    ],
    "CNViz": [
        "CopyNumberPlots",
        "biovizBase",
        "karyoploteR"
    ],
    "CNVrd2": [],
    "COCOA": [
        "MIRA"
    ],
    "Cogito": [],
    "comapr": [
        "Gviz",
        "biovizBase"
    ],
    "coMET": [
        "Gviz",
        "biovizBase"
    ],
    "coMethDMR": [],
    "compEpiTools": [
        "Gviz",
        "biovizBase",
        "methylPipe"
    ],
    "condiments": [
        "distinct"
    ],
    "consensusDE": [],
    "contiBAIT": [
        "GenomicFiles"
    ],
    "conumee": [],
    "CopyNumberPlots": [
        "biovizBase",
        "karyoploteR"
    ],
    "cpvSNP": [],
    "crisprBwa": [],
    "crisprDesign": [],
    "CRISPRseek": [],
    "crisprseekplus": [
        "CRISPRseek",
        "ChIPpeakAnno",
        "GUIDEseq"
    ],
    "crisprVerse": [
        "Gviz",
        "biovizBase",
        "crisprDesign",
        "crisprViz"
    ],
    "crisprViz": [
        "Gviz",
        "biovizBase",
        "crisprDesign"
    ],
    "crossmeta": [],
    "CSSQ": [],
    "CTdata": [],
    "CTSV": [],
    "cummeRbund": [
        "Gviz",
        "biovizBase"
    ],
    "customProDB": [],
    "cyanoFilter": [
        "flowDensity"
    ],
    "cytofQC": [],
    "dagLogo": [
        "motifStack"
    ],
    "DAMEfinder": [],
    "DaMiRseq": [],
    "dasper": [],
    "ddPCRclust": [
        "flowDensity"
    ],
    "decompTumor2Sig": [],
    "deconvR": [],
    "DeepBlueR": [],
    "deepSNV": [],
    "DEGraph": [
        "NCIgraph",
        "RCy3"
    ],
    "DeMixT": [
        "DSS"
    ],
    "derfinder": [
        "GenomicFiles"
    ],
    "derfinderPlot": [
        "GenomicFiles",
        "biovizBase",
        "derfinder",
        "ggbio"
    ],
    "DEScan2": [
        "ChIPpeakAnno"
    ],
    "DiffBind": [],
    "distinct": [],
    "DMRcate": [
        "DSS",
        "Gviz",
        "biovizBase",
        "methylumi",
        "missMethyl"
    ],
    "DMRforPairs": [
        "Gviz",
        "biovizBase"
    ],
    "dmrseq": [
        "annotatr"
    ],
    "DominoEffect": [],
    "doubletrouble": [],
    "DSS": [],
    "ELMER": [
        "Gviz",
        "biovizBase"
    ],
    "enhancerHomologSearch": [
        "motifmatchr"
    ],
    "ENmix": [],
    "enrichTF": [
        "motifmatchr"
    ],
    "ensemblVEP": [],
    "epialleleR": [],
    "EpiCompare": [],
    "epigraHMM": [],
    "EpiMix": [],
    "epimutacions": [
        "Gviz",
        "biovizBase"
    ],
    "epivizr": [
        "epivizrData"
    ],
    "epivizrChart": [
        "epivizrData"
    ],
    "epivizrData": [],
    "epivizrStandalone": [
        "epivizr",
        "epivizrData"
    ],
    "erma": [
        "GenomicFiles"
    ],
    "esATAC": [
        "motifmatchr"
    ],
    "ExperimentHubData": [
        "AnnotationHubData"
    ],
    "extraChIPs": [
        "GenomicInteractions",
        "Gviz",
        "biovizBase"
    ],
    "factR": [],
    "fCCAC": [],
    "fcScan": [],
    "fedup": [
        "RCy3"
    ],
    "ffpe": [
        "lumi",
        "methylumi"
    ],
    "fgga": [],
    "FLAMES": [
        "biovizBase",
        "ggbio"
    ],
    "flowCut": [
        "flowDensity"
    ],
    "flowDensity": [],
    "funtooNorm": [],
    "GA4GHclient": [],
    "GA4GHshiny": [
        "GA4GHclient"
    ],
    "GARS": [
        "DaMiRseq"
    ],
    "gcapc": [],
    "genbankr": [],
    "geneAttribution": [],
    "GeneStructureTools": [
        "Gviz",
        "biovizBase"
    ],
    "GenomicFiles": [],
    "GenomicInteractions": [
        "Gviz",
        "biovizBase"
    ],
    "GenomicOZone": [
        "biovizBase",
        "ggbio"
    ],
    "GenVisR": [],
    "GEOexplorer": [],
    "ggbio": [
        "biovizBase"
    ],
    "gmapR": [],
    "gmoviz": [],
    "GRaNIE": [],
    "GSReg": [],
    "GUIDEseq": [
        "CRISPRseek",
        "ChIPpeakAnno"
    ],
    "Gviz": [
        "biovizBase"
    ],
    "gwascat": [],
    "gwasurvivr": [],
    "HelloRanges": [],
    "HiCDCPlus": [
        "GenomicInteractions",
        "Gviz",
        "biovizBase"
    ],
    "HiCDOC": [],
    "hiReadsProcessor": [],
    "hpar": [],
    "HTSeqGenie": [
        "VariantTools",
        "gmapR"
    ],
    "icetea": [],
    "iCheck": [
        "lumi",
        "methylumi"
    ],
    "iCNV": [],
    "igvR": [],
    "IMAS": [
        "IVAS"
    ],
    "InPAS": [],
    "INSPEcT": [],
    "intansv": [
        "biovizBase",
        "ggbio"
    ],
    "IntEREst": [
        "GenomicFiles"
    ],
    "IsoformSwitchAnalyzeR": [
        "tximeta"
    ],
    "IVAS": [],
    "karyoploteR": [
        "biovizBase"
    ],
    "katdetectr": [],
    "kissDE": [
        "DSS"
    ],
    "lineagespot": [],
    "lisaClust": [
        "spicyR"
    ],
    "lumi": [
        "methylumi"
    ],
    "MADSEQ": [],
    "MAGAR": [
        "RnBeads",
        "methylumi"
    ],
    "MAGeCKFlute": [],
    "maser": [
        "Gviz",
        "biovizBase"
    ],
    "MatrixRider": [],
    "mCSEA": [
        "Gviz",
        "biovizBase"
    ],
    "MEAL": [
        "Gviz",
        "biovizBase",
        "methylumi",
        "missMethyl"
    ],
    "MEAT": [
        "lumi",
        "methylumi",
        "wateRmelon"
    ],
    "MetaboSignal": [
        "hpar"
    ],
    "MetaPhOR": [
        "RCy3"
    ],
    "MethylAid": [],
    "methylCC": [],
    "methylclock": [
        "AnnotationHubData",
        "ExperimentHubData"
    ],
    "methylGSA": [
        "methylumi",
        "missMethyl"
    ],
    "methylPipe": [
        "Gviz",
        "biovizBase"
    ],
    "methylSig": [
        "DSS"
    ],
    "methylumi": [],
    "MineICA": [
        "lumi",
        "methylumi"
    ],
    "MinimumDistance": [],
    "MIRA": [],
    "miRSM": [
        "miRspongeR"
    ],
    "miRspongeR": [],
    "missMethyl": [
        "methylumi"
    ],
    "mitoClone2": [
        "deepSNV"
    ],
    "MMAPPR2": [
        "VariantTools",
        "ensemblVEP",
        "gmapR"
    ],
    "MOGAMUN": [
        "RCy3"
    ],
    "MoleculeExperiment": [],
    "monaLisa": [],
    "motifbreakR": [
        "Gviz",
        "biovizBase",
        "motifStack"
    ],
    "motifmatchr": [],
    "motifStack": [],
    "MsDataHub": [],
    "msgbsR": [
        "biovizBase",
        "ggbio"
    ],
    "MsQuality": [],
    "multicrispr": [
        "CRISPRseek",
        "biovizBase",
        "karyoploteR"
    ],
    "multiGSEA": [],
    "MungeSumstats": [],
    "musicatk": [
        "decompTumor2Sig"
    ],
    "MutationalPatterns": [],
    "myvariant": [],
    "NADfinder": [
        "ATACseqQC",
        "ChIPpeakAnno",
        "Gviz",
        "biovizBase",
        "motifStack",
        "trackViewer"
    ],
    "NanoMethViz": [],
    "NCIgraph": [
        "RCy3"
    ],
    "nearBynding": [],
    "netZooR": [
        "RCy3",
        "quantro",
        "yarn"
    ],
    "octad": [],
    "ODER": [
        "GenomicFiles",
        "dasper",
        "derfinder"
    ],
    "OGRE": [
        "Gviz",
        "biovizBase"
    ],
    "omada": [],
    "OmicsLonDA": [],
    "OMICsPCA": [
        "HelloRanges"
    ],
    "ORFhunteR": [],
    "OutSplice": [],
    "pageRank": [
        "motifmatchr"
    ],
    "PhIPData": [],
    "PING": [
        "Gviz",
        "biovizBase"
    ],
    "pipeComp": [],
    "preciseTAD": [],
    "primirTSS": [
        "Gviz",
        "biovizBase"
    ],
    "proBAMr": [],
    "profileplyr": [],
    "proteasy": [],
    "ProteoDisco": [],
    "psichomics": [
        "GenomicFiles",
        "derfinder",
        "recount"
    ],
    "PureCN": [],
    "Pviz": [
        "Gviz",
        "biovizBase"
    ],
    "quantro": [],
    "QuasR": [
        "GenomicFiles"
    ],
    "R3CPET": [
        "biovizBase",
        "ggbio"
    ],
    "R453Plus1Toolbox": [],
    "RareVariantVis": [],
    "RCAS": [],
    "RCy3": [],
    "recount": [
        "GenomicFiles",
        "derfinder"
    ],
    "recountmethylation": [],
    "recoup": [],
    "REDseq": [
        "ChIPpeakAnno"
    ],
    "regioneReloaded": [],
    "regionReport": [
        "GenomicFiles",
        "derfinder"
    ],
    "regutools": [
        "Gviz",
        "RCy3",
        "biovizBase"
    ],
    "REMP": [],
    "ReportingTools": [
        "biovizBase",
        "ggbio"
    ],
    "RESOLVE": [
        "MutationalPatterns"
    ],
    "RgnTX": [],
    "RiboCrypt": [],
    "RiboProfiling": [
        "biovizBase",
        "ggbio"
    ],
    "ribosomeProfilingQC": [
        "motifStack"
    ],
    "RIPAT": [
        "biovizBase",
        "karyoploteR"
    ],
    "RITAN": [],
    "RLSeq": [],
    "Rmmquant": [],
    "RNAAgeCalc": [
        "GenomicFiles",
        "derfinder",
        "recount"
    ],
    "RNAmodR": [
        "Gviz",
        "biovizBase"
    ],
    "RNAmodR.AlkAnilineSeq": [
        "Gviz",
        "RNAmodR",
        "biovizBase"
    ],
    "RNAmodR.ML": [
        "Gviz",
        "RNAmodR",
        "biovizBase"
    ],
    "RNAmodR.RiboMethSeq": [
        "Gviz",
        "RNAmodR",
        "biovizBase"
    ],
    "RnaSeqSampleSize": [
        "GenomicFiles",
        "derfinder",
        "recount"
    ],
    "RnBeads": [
        "methylumi"
    ],
    "Rqc": [
        "GenomicFiles",
        "biovizBase"
    ],
    "RTCGAToolbox": [],
    "scanMiRApp": [],
    "SCATE": [],
    "scmeth": [
        "annotatr"
    ],
    "scone": [],
    "scoreInvHap": [],
    "scRNAseqApp": [],
    "scruff": [
        "biovizBase",
        "ggbio"
    ],
    "scTreeViz": [
        "epivizr",
        "epivizrData"
    ],
    "selectKSigs": [],
    "seqArchRplus": [],
    "seqCAT": [],
    "SeqSQC": [],
    "shinyepico": [],
    "shinyMethyl": [],
    "signatureSearch": [],
    "signeR": [],
    "signifinder": [],
    "SigsPack": [],
    "singleCellTK": [
        "celda"
    ],
    "SingleMoleculeFootprinting": [
        "GenomicFiles",
        "QuasR"
    ],
    "skewr": [
        "lumi",
        "methylumi",
        "wateRmelon"
    ],
    "SNPhood": [],
    "SomaticSignatures": [
        "biovizBase",
        "ggbio"
    ],
    "spatzie": [
        "GenomicInteractions",
        "Gviz",
        "biovizBase",
        "motifmatchr"
    ],
    "spicyR": [],
    "SPLINTER": [
        "Gviz",
        "biovizBase"
    ],
    "standR": [],
    "Statial": [],
    "stJoincount": [],
    "strandCheckR": [],
    "StructuralVariantAnnotation": [],
    "svaNUMT": [
        "StructuralVariantAnnotation"
    ],
    "svaRetro": [
        "StructuralVariantAnnotation"
    ],
    "terraTCGAdata": [],
    "TFEA.ChIP": [],
    "TFHAZ": [],
    "TimiRGeN": [
        "RCy3"
    ],
    "TitanCNA": [],
    "tLOH": [],
    "trackViewer": [
        "Gviz",
        "biovizBase"
    ],
    "transomics2cytoscape": [
        "RCy3"
    ],
    "trena": [],
    "tscR": [],
    "TVTB": [
        "Gviz",
        "biovizBase",
        "ensemblVEP"
    ],
    "txcutr": [],
    "tximeta": [],
    "Ularcirc": [],
    "UMI4Cats": [],
    "uncoverappLib": [
        "Gviz",
        "biovizBase"
    ],
    "Uniquorn": [],
    "VariantFiltering": [
        "Gviz",
        "biovizBase"
    ],
    "VariantTools": [],
    "VCFArray": [
        "GenomicFiles"
    ],
    "vtpnet": [
        "gwascat"
    ],
    "vulcan": [
        "ChIPpeakAnno",
        "DiffBind"
    ],
    "waddR": [],
    "wateRmelon": [
        "lumi",
        "methylumi"
    ],
    "Xeva": [],
    "YAPSA": [
        "SomaticSignatures",
        "biovizBase",
        "ggbio"
    ],
    "yarn": [
        "quantro"
    ],
    "ZygosityPredictor": []
}